[
  {
    "timestamp": "2026-05-28T11:00:38.467324",
    "queries": [
      {
        "query": "(\"Junior Data Scientist\" OR \"Entry Level Machine Learning Engineer\" OR \"Graduate\") AND (Python OR Java OR \"Data Analysis\") AND (\"Team Collaboration\" OR \"Problem Solving\")",
        "jobs": []
      },
      {
        "query": "(\"Junior\" OR \"Entry Level\" OR \"Intern\") AND (\"Data Science\" OR \"Machine Learning\" OR \"AI\") AND (Python OR Java OR \"Data Analysis\")",
        "jobs": []
      },
      {
        "query": "(\"Entry Level\" OR \"Junior\" OR \"Intern\") AND (\"Full Stack Developer\" OR \"Frontend Developer\" OR \"Backend Developer\") AND (React OR Node.js OR Python OR Django OR \"REST API\")",
        "jobs": [
          {
            "title": "Remote Fullstack Engineer",
            "company": "Turing",
            "score": 40,
            "sent": false
          },
          {
            "title": "Remote Fullstack Engineer",
            "company": "Turing",
            "score": 80,
            "sent": true
          }
        ]
      },
      {
        "query": "(\"Data Scientist\" OR \"Machine Learning Engineer\" OR \"AI Engineer\") AND (Python OR Java OR \"Data Analysis\") AND (\"Computer Vision\" OR \"Artificial Intelligence\")",
        "jobs": [
          {
            "title": "Senior ML-Engineer",
            "company": "Fundraise Up",
            "score": 10,
            "sent": false
          }
        ]
      },
      {
        "query": "(\"Junior\" OR \"Entry Level\" OR \"Intern\") AND (\"Data Science\" OR \"Machine Learning\" OR \"AI\") AND (Python OR Java OR \"Data Analysis\") AND (\"Team Collaboration\" OR \"Problem Solving\")",
        "jobs": []
      }
    ]
  },
  {
    "timestamp": "2026-05-28T15:54:10.817502",
    "queries": [
      {
        "query": "(\"Junior Data Scientist\" OR \"Entry Level Machine Learning Engineer\" OR \"Graduate\") AND (Python OR Java OR \"Data Analysis\") AND (\"Team Collaboration\" OR \"Problem Solving\")",
        "jobs": []
      },
      {
        "query": "(\"Junior\" OR \"Entry Level\" OR \"Intern\") AND (\"Data Science\" OR \"Machine Learning\" OR \"AI\") AND (Python OR Java OR \"Data Analysis\")",
        "jobs": []
      },
      {
        "query": "(\"Entry Level\" OR \"Junior\" OR \"Intern\") AND (\"Full Stack Developer\" OR \"Frontend Developer\" OR \"Backend Developer\") AND (React OR Node.js OR Python OR Django OR \"REST API\")",
        "jobs": []
      },
      {
        "query": "(\"Data Scientist\" OR \"Machine Learning Engineer\" OR \"AI Engineer\") AND (Python OR Java OR \"Data Analysis\") AND (\"Computer Vision\" OR \"Artificial Intelligence\")",
        "jobs": [
          {
            "title": "Robotics Software Engineer",
            "company": "RB-Ware",
            "score": 40,
            "sent": false
          }
        ]
      },
      {
        "query": "(\"Junior\" OR \"Entry Level\" OR \"Intern\") AND (\"Data Science\" OR \"Machine Learning\" OR \"AI\") AND (Python OR Java OR \"Data Analysis\") AND (\"Team Collaboration\" OR \"Problem Solving\")",
        "jobs": []
      }
    ]
  },
  {
    "timestamp": "2026-05-28T19:38:46.617055",
    "queries": [
      {
        "query": "(\"Junior Data Scientist\" OR \"Entry Level Machine Learning Engineer\" OR \"Graduate\") AND (Python OR Java OR \"Data Analysis\") AND (\"Team Collaboration\" OR \"Problem Solving\")",
        "jobs": []
      },
      {
        "query": "(\"Junior\" OR \"Entry Level\" OR \"Intern\") AND (\"Data Science\" OR \"Machine Learning\" OR \"AI\") AND (Python OR Java OR \"Data Analysis\")",
        "jobs": []
      },
      {
        "query": "(\"Entry Level\" OR \"Junior\" OR \"Intern\") AND (\"Full Stack Developer\" OR \"Frontend Developer\" OR \"Backend Developer\") AND (React OR Node.js OR Python OR Django OR \"REST API\")",
        "jobs": []
      },
      {
        "query": "(\"Data Scientist\" OR \"Machine Learning Engineer\" OR \"AI Engineer\") AND (Python OR Java OR \"Data Analysis\") AND (\"Computer Vision\" OR \"Artificial Intelligence\")",
        "jobs": []
      },
      {
        "query": "(\"Junior\" OR \"Entry Level\" OR \"Intern\") AND (\"Data Science\" OR \"Machine Learning\" OR \"AI\") AND (Python OR Java OR \"Data Analysis\") AND (\"Team Collaboration\" OR \"Problem Solving\")",
        "jobs": []
      }
    ]
  },
  {
    "timestamp": "2026-05-29T10:51:48.923772",
    "queries": [
      {
        "query": "(\"Junior Data Scientist\" OR \"Entry Level Machine Learning Engineer\" OR \"Graduate\") AND (Python OR Java OR \"Data Analysis\") AND (\"Team Collaboration\" OR \"Problem Solving\")",
        "jobs": [
          {
            "title": "Sustainability Associate (CER)",
            "company": "Bureau Veritas",
            "score": 40,
            "sent": false
          }
        ]
      },
      {
        "query": "(\"Junior\" OR \"Entry Level\" OR \"Intern\") AND (\"Data Science\" OR \"Machine Learning\" OR \"AI\") AND (Python OR Java OR \"Data Analysis\")",
        "jobs": [
          {
            "title": "Sustainability Associate (CER)",
            "company": "Bureau Veritas",
            "score": 40,
            "sent": false
          },
          {
            "title": "ML and Optimization Engineer",
            "company": "National Laboratory of the Rockies",
            "score": 80,
            "sent": true
          }
        ]
      },
      {
        "query": "(\"Entry Level\" OR \"Junior\" OR \"Intern\") AND (\"Full Stack Developer\" OR \"Frontend Developer\" OR \"Backend Developer\") AND (React OR Node.js OR Python OR Django OR \"REST API\")",
        "jobs": []
      },
      {
        "query": "(\"Data Scientist\" OR \"Machine Learning Engineer\" OR \"AI Engineer\") AND (Python OR Java OR \"Data Analysis\") AND (\"Computer Vision\" OR \"Artificial Intelligence\")",
        "jobs": []
      },
      {
        "query": "(\"Junior\" OR \"Entry Level\" OR \"Intern\") AND (\"Data Science\" OR \"Machine Learning\" OR \"AI\") AND (Python OR Java OR \"Data Analysis\") AND (\"Team Collaboration\" OR \"Problem Solving\")",
        "jobs": [
          {
            "title": "Sustainability Associate (CER)",
            "company": "Bureau Veritas",
            "score": 40,
            "sent": false
          },
          {
            "title": "ML and Optimization Engineer",
            "company": "National Laboratory of the Rockies",
            "score": 80,
            "sent": true
          }
        ]
      }
    ]
  },
  {
    "timestamp": "2026-05-29T15:30:19.798822",
    "queries": [
      {
        "query": "(\"Junior Data Scientist\" OR \"Entry Level Machine Learning Engineer\" OR \"Graduate\") AND (Python OR Java OR \"Data Analysis\") AND (\"Team Collaboration\" OR \"Problem Solving\")",
        "jobs": []
      },
      {
        "query": "(\"Junior\" OR \"Entry Level\" OR \"Intern\") AND (\"Data Science\" OR \"Machine Learning\" OR \"AI\") AND (Python OR Java OR \"Data Analysis\")",
        "jobs": [
          {
            "title": "Lilly StarT HR Intern",
            "company": "Eli Lilly and Company",
            "score": 10,
            "sent": false
          }
        ]
      },
      {
        "query": "(\"Entry Level\" OR \"Junior\" OR \"Intern\") AND (\"Full Stack Developer\" OR \"Frontend Developer\" OR \"Backend Developer\") AND (React OR Node.js OR Python OR Django OR \"REST API\")",
        "jobs": []
      },
      {
        "query": "(\"Data Scientist\" OR \"Machine Learning Engineer\" OR \"AI Engineer\") AND (Python OR Java OR \"Data Analysis\") AND (\"Computer Vision\" OR \"Artificial Intelligence\")",
        "jobs": []
      },
      {
        "query": "(\"Junior\" OR \"Entry Level\" OR \"Intern\") AND (\"Data Science\" OR \"Machine Learning\" OR \"AI\") AND (Python OR Java OR \"Data Analysis\") AND (\"Team Collaboration\" OR \"Problem Solving\")",
        "jobs": [
          {
            "title": "Lilly StarT HR Intern",
            "company": "Eli Lilly and Company",
            "score": 10,
            "sent": false
          }
        ]
      }
    ]
  },
  {
    "timestamp": "2026-05-29T19:33:51.333920",
    "queries": [
      {
        "query": "(\"Junior Data Scientist\" OR \"Entry Level Machine Learning Engineer\" OR \"Graduate\") AND (Python OR Java OR \"Data Analysis\") AND (\"Team Collaboration\" OR \"Problem Solving\")",
        "jobs": []
      },
      {
        "query": "(\"Junior\" OR \"Entry Level\" OR \"Intern\") AND (\"Data Science\" OR \"Machine Learning\" OR \"AI\") AND (Python OR Java OR \"Data Analysis\")",
        "jobs": [
          {
            "title": "Yapay Zeka Mühendisi Stajer",
            "company": "C'esta Technology",
            "score": 85,
            "sent": true
          }
        ]
      },
      {
        "query": "(\"Entry Level\" OR \"Junior\" OR \"Intern\") AND (\"Full Stack Developer\" OR \"Frontend Developer\" OR \"Backend Developer\") AND (React OR Node.js OR Python OR Django OR \"REST API\")",
        "jobs": []
      },
      {
        "query": "(\"Data Scientist\" OR \"Machine Learning Engineer\" OR \"AI Engineer\") AND (Python OR Java OR \"Data Analysis\") AND (\"Computer Vision\" OR \"Artificial Intelligence\")",
        "jobs": [
          {
            "title": "SAP AI Core & GenAI Engineer",
            "company": "iSoftStone",
            "score": 80,
            "sent": true
          },
          {
            "title": "AI Content Creator",
            "company": "KEFİLİN YAZILIM A.Ş",
            "score": 40,
            "sent": false
          }
        ]
      },
      {
        "query": "(\"Junior\" OR \"Entry Level\" OR \"Intern\") AND (\"Data Science\" OR \"Machine Learning\" OR \"AI\") AND (Python OR Java OR \"Data Analysis\") AND (\"Team Collaboration\" OR \"Problem Solving\")",
        "jobs": []
      }
    ]
  },
  {
    "timestamp": "2026-05-30T09:24:01.905599",
    "queries": [
      {
        "query": "(\"Junior Data Scientist\" OR \"Entry Level Machine Learning Engineer\" OR \"Graduate\") AND (Python OR Java OR \"Data Analysis\") AND (\"Team Collaboration\" OR \"Problem Solving\")",
        "jobs": [
          {
            "title": "Senior Risk Operations Manager",
            "company": "Uber",
            "score": 10,
            "sent": false
          }
        ]
      },
      {
        "query": "(\"Junior\" OR \"Entry Level\" OR \"Intern\") AND (\"Data Science\" OR \"Machine Learning\" OR \"AI\") AND (Python OR Java OR \"Data Analysis\")",
        "jobs": [
          {
            "title": "Senior Data Engineer - Quant & AI Infrastructure",
            "company": "Algocor",
            "score": 10,
            "sent": false
          },
          {
            "title": "Senior Software Developer (Core Platform, Rust/Go)",
            "company": "Acronis",
            "score": 10,
            "sent": false
          }
        ]
      },
      {
        "query": "(\"Entry Level\" OR \"Junior\" OR \"Intern\") AND (\"Full Stack Developer\" OR \"Frontend Developer\" OR \"Backend Developer\") AND (React OR Node.js OR Python OR Django OR \"REST API\")",
        "jobs": []
      },
      {
        "query": "(\"Data Scientist\" OR \"Machine Learning Engineer\" OR \"AI Engineer\") AND (Python OR Java OR \"Data Analysis\") AND (\"Computer Vision\" OR \"Artificial Intelligence\")",
        "jobs": []
      },
      {
        "query": "(\"Junior\" OR \"Entry Level\" OR \"Intern\") AND (\"Data Science\" OR \"Machine Learning\" OR \"AI\") AND (Python OR Java OR \"Data Analysis\") AND (\"Team Collaboration\" OR \"Problem Solving\")",
        "jobs": [
          {
            "title": "Senior Software Developer (Core Platform, Rust/Go)",
            "company": "Acronis",
            "score": 10,
            "sent": false
          }
        ]
      }
    ]
  },
  {
    "timestamp": "2026-05-30T13:29:15.400287",
    "queries": [
      {
        "query": "(\"Junior Data Scientist\" OR \"Entry Level Machine Learning Engineer\" OR \"Graduate\") AND (Python OR Java OR \"Data Analysis\") AND (\"Team Collaboration\" OR \"Problem Solving\")",
        "jobs": []
      },
      {
        "query": "(\"Junior\" OR \"Entry Level\" OR \"Intern\") AND (\"Data Science\" OR \"Machine Learning\" OR \"AI\") AND (Python OR Java OR \"Data Analysis\")",
        "jobs": []
      },
      {
        "query": "(\"Entry Level\" OR \"Junior\" OR \"Intern\") AND (\"Full Stack Developer\" OR \"Frontend Developer\" OR \"Backend Developer\") AND (React OR Node.js OR Python OR Django OR \"REST API\")",
        "jobs": []
      },
      {
        "query": "(\"Data Scientist\" OR \"Machine Learning Engineer\" OR \"AI Engineer\") AND (Python OR Java OR \"Data Analysis\") AND (\"Computer Vision\" OR \"Artificial Intelligence\")",
        "jobs": []
      },
      {
        "query": "(\"Junior\" OR \"Entry Level\" OR \"Intern\") AND (\"Data Science\" OR \"Machine Learning\" OR \"AI\") AND (Python OR Java OR \"Data Analysis\") AND (\"Team Collaboration\" OR \"Problem Solving\")",
        "jobs": []
      }
    ]
  },
  {
    "timestamp": "2026-05-30T18:05:27.733179",
    "queries": [
      {
        "query": "(\"Junior Data Scientist\" OR \"Entry Level Machine Learning Engineer\" OR \"Graduate\") AND (Python OR Java OR \"Data Analysis\") AND (\"Team Collaboration\" OR \"Problem Solving\")",
        "jobs": []
      },
      {
        "query": "(\"Junior\" OR \"Entry Level\" OR \"Intern\") AND (\"Data Science\" OR \"Machine Learning\" OR \"AI\") AND (Python OR Java OR \"Data Analysis\")",
        "jobs": [
          {
            "title": "Senior Frontend Developer",
            "company": "Acronis",
            "score": 10,
            "sent": false
          }
        ]
      },
      {
        "query": "(\"Entry Level\" OR \"Junior\" OR \"Intern\") AND (\"Full Stack Developer\" OR \"Frontend Developer\" OR \"Backend Developer\") AND (React OR Node.js OR Python OR Django OR \"REST API\")",
        "jobs": [
          {
            "title": "Senior Frontend Developer",
            "company": "Acronis",
            "score": 10,
            "sent": false
          }
        ]
      },
      {
        "query": "(\"Data Scientist\" OR \"Machine Learning Engineer\" OR \"AI Engineer\") AND (Python OR Java OR \"Data Analysis\") AND (\"Computer Vision\" OR \"Artificial Intelligence\")",
        "jobs": []
      },
      {
        "query": "(\"Junior\" OR \"Entry Level\" OR \"Intern\") AND (\"Data Science\" OR \"Machine Learning\" OR \"AI\") AND (Python OR Java OR \"Data Analysis\") AND (\"Team Collaboration\" OR \"Problem Solving\")",
        "jobs": [
          {
            "title": "Senior Frontend Developer",
            "company": "Acronis",
            "score": 10,
            "sent": false
          }
        ]
      }
    ]
  }
]